odoo/addons/redis_session_store/__init__.py
odoo/addons/redis_session_store/__manifest__.py
odoo/addons/redis_session_store/json_encoding.py
odoo/addons/redis_session_store/patcher.py
odoo/addons/redis_session_store/redis_config.py
odoo/addons/redis_session_store/redis_session.py
mangono_odoo_redis_session-1.4.1.dist-info/METADATA
mangono_odoo_redis_session-1.4.1.dist-info/WHEEL
mangono_odoo_redis_session-1.4.1.dist-info/RECORD
