Metadata-Version: 2.4
Name: mangono-odoo-redis-session
Version: 1.4.1
Summary: Module to store session on a redis
Author-email: Alexis PASQUIER <alexis.pasquier@mangono.fr>
Requires-Python: >=3.8.19
Requires-Dist: redis~=5.0
Requires-Dist: wrapt<2,>=1.17.0
